{
  "$id": "137138",
  "$schema": "https://schema.yext.com/config/km/entity/v1",
  "primaryLocale": "en",
  "content": {
    "c_runningTime": "Approx 2 hours 30 minutes, incl interval",
    "c_showType": "Play",
    "c_tags": [
      "a list star",
      "drama",
      "hot tickets",
      "limited run",
      "shakespeare",
      "plays"
    ],
    "c_venueAddress": "Dock X, Retail Park, Unit 1 Canada Water, Surrey Quays Rd, London SE16 2XU",
    "c_venueName": "Dock X",
    "landingPageUrl": "https://lovetheatre.akaagencies.com/shows/macbeth-tickets/",
    "name": "Macbeth",
    "price": {
      "currencyCode": "GBP"
    },
    "primaryPhoto": {
      "description": "A brand new production of The Scottish Play, MACBETH, is coming to Dock X for a strictly limited run.\nOnce you cross the line, you can never turn back.\nStarring Ralph Fiennes and Indira Varma, this new production of one of William Shakespeare‘s most iconic plays will be seen like never before, with direction from Simon Goodwin and costume and set design by Frankie Bradshaw.\nBook your MACBETH theatre tickets with LOVEtheatre today!",
      "image": {
        "height": 1080,
        "sourceUrl": "https://www.lovetheatre.com/content/uploads/2022/11/MACBETH24_Q1_014_LOVE_THEATRE_1080x1080px_V1_AW.jpg",
        "thumbnails": [
          {
            "height": 1080,
            "url": "http://a.mktgcdn.com/p-sandbox/DJ9AaUBXVee_Ykr1CL0R_7RSzO3HAjNc0bLROCVKvJU/1080x1080.jpg",
            "width": 1080
          },
          {
            "height": 619,
            "url": "http://a.mktgcdn.com/p-sandbox/DJ9AaUBXVee_Ykr1CL0R_7RSzO3HAjNc0bLROCVKvJU/619x619.jpg",
            "width": 619
          },
          {
            "height": 450,
            "url": "http://a.mktgcdn.com/p-sandbox/DJ9AaUBXVee_Ykr1CL0R_7RSzO3HAjNc0bLROCVKvJU/450x450.jpg",
            "width": 450
          },
          {
            "height": 196,
            "url": "http://a.mktgcdn.com/p-sandbox/DJ9AaUBXVee_Ykr1CL0R_7RSzO3HAjNc0bLROCVKvJU/196x196.jpg",
            "width": 196
          }
        ],
        "url": "http://a.mktgcdn.com/p-sandbox/DJ9AaUBXVee_Ykr1CL0R_7RSzO3HAjNc0bLROCVKvJU/1080x1080.jpg",
        "width": 1080
      }
    }
  },
  "entityType": "ce_show",
  "labels": []
}