{
  "$id": "1614",
  "$schema": "https://schema.yext.com/config/km/entity/v1",
  "primaryLocale": "en",
  "content": {
    "c_answer2": "The West End run of Tina Turner is scheduled to continue until 14th Sep 2024. At this stage there are no plans for the show to go on tour but if that changes you can be sure to find out via LOVEtheatre.",
    "c_show": [
      "161"
    ],
    "c_type": "SHOW",
    "name": "Is Tina Turner the musical touring?",
    "question": "Is Tina Turner the musical touring?"
  },
  "entityType": "faq",
  "labels": []
}