{
  "$id": "5231",
  "$schema": "https://schema.yext.com/config/km/entity/v1",
  "primaryLocale": "en",
  "content": {
    "c_answer2": "Only Fools and Horses The Musical is coming to the Eventim Apollo in London, following a successful 4 year run in the West End",
    "c_show": [
      "523"
    ],
    "c_type": "SHOW",
    "name": "Where is Only Fools and Horses The Musical playing?",
    "question": "Where is Only Fools and Horses The Musical playing?"
  },
  "entityType": "faq",
  "labels": []
}